Workbook

Sheet Resumen
A1: MÉXICO — NRR DE JUNIO 2026, BASE MENSUAL, POR SEGMENTO DE TAMAÑO
A2: NRR del mes X = MRR de la cohorte en X / MRR en X-12 (cohorte = conglomerados de México con MRR > 0 en X-12; los creados después quedan fuera). Todo en MXN; USD sólo para segmentar (TC del mes base). Fuga = MRR actual = 0. GRR = MIN(actual; base) / base (retención sin expansión).
B4: NRR 2026-06 (vs 2025-06)
A5: Segmento | B5: N | C5: Fuga (n) | D5: % Fuga | E5: GRR | F5: NRR
A6: Menos de 100 USD | B6: =COUNTIFS('Detalle 2026-06'!C2:C784,">0",'Detalle 2026-06'!G2:G784,"Menos de 100 USD") -> 125 | C6: =COUNTIFS('Detalle 2026-06'!C2:C784,">0",'Detalle 2026-06'!D2:D784,"<=0",'Detalle 2026-06'!G2:G784,"Menos de 100 USD") -> 46 | D6: =IFERROR(COUNTIFS('Detalle 2026-06'!C2:C784,">0",'Detalle 2026-06'!D2:D784,"<=0",'Detalle 2026-06'!G2:G784,"Menos de 100 USD")/COUNTIFS('Detalle 2026-06'!C2:C784,">0",'Detalle 2026-06'!G2:G784,"Menos de 100 USD"),"") -> 0.368 | E6: =IFERROR(SUMIFS('Detalle 2026-06'!H2:H784,'Detalle 2026-06'!G2:G784,"Menos de 100 USD")/SUMIFS('Detalle 2026-06'!C2:C784,'Detalle 2026-06'!G2:G784,"Menos de 100 USD"),"") -> 0.65358351 | F6: =IFERROR(SUMIFS('Detalle 2026-06'!D2:D784,'Detalle 2026-06'!G2:G784,"Menos de 100 USD")/SUMIFS('Detalle 2026-06'!C2:C784,'Detalle 2026-06'!G2:G784,"Menos de 100 USD"),"") -> 0.91827528
A7: 100 a 500 USD | B7: =COUNTIFS('Detalle 2026-06'!C2:C784,">0",'Detalle 2026-06'!G2:G784,"100 a 500 USD") -> 166 | C7: =COUNTIFS('Detalle 2026-06'!C2:C784,">0",'Detalle 2026-06'!D2:D784,"<=0",'Detalle 2026-06'!G2:G784,"100 a 500 USD") -> 31 | D7: =IFERROR(COUNTIFS('Detalle 2026-06'!C2:C784,">0",'Detalle 2026-06'!D2:D784,"<=0",'Detalle 2026-06'!G2:G784,"100 a 500 USD")/COUNTIFS('Detalle 2026-06'!C2:C784,">0",'Detalle 2026-06'!G2:G784,"100 a 500 USD"),"") -> 0.18674699 | E7: =IFERROR(SUMIFS('Detalle 2026-06'!H2:H784,'Detalle 2026-06'!G2:G784,"100 a 500 USD")/SUMIFS('Detalle 2026-06'!C2:C784,'Detalle 2026-06'!G2:G784,"100 a 500 USD"),"") -> 0.71604021 | F7: =IFERROR(SUMIFS('Detalle 2026-06'!D2:D784,'Detalle 2026-06'!G2:G784,"100 a 500 USD")/SUMIFS('Detalle 2026-06'!C2:C784,'Detalle 2026-06'!G2:G784,"100 a 500 USD"),"") -> 0.93279317
A8: 500 a 2.000 USD | B8: =COUNTIFS('Detalle 2026-06'!C2:C784,">0",'Detalle 2026-06'!G2:G784,"500 a 2.000 USD") -> 51 | C8: =COUNTIFS('Detalle 2026-06'!C2:C784,">0",'Detalle 2026-06'!D2:D784,"<=0",'Detalle 2026-06'!G2:G784,"500 a 2.000 USD") -> 9 | D8: =IFERROR(COUNTIFS('Detalle 2026-06'!C2:C784,">0",'Detalle 2026-06'!D2:D784,"<=0",'Detalle 2026-06'!G2:G784,"500 a 2.000 USD")/COUNTIFS('Detalle 2026-06'!C2:C784,">0",'Detalle 2026-06'!G2:G784,"500 a 2.000 USD"),"") -> 0.17647059 | E8: =IFERROR(SUMIFS('Detalle 2026-06'!H2:H784,'Detalle 2026-06'!G2:G784,"500 a 2.000 USD")/SUMIFS('Detalle 2026-06'!C2:C784,'Detalle 2026-06'!G2:G784,"500 a 2.000 USD"),"") -> 0.75998045 | F8: =IFERROR(SUMIFS('Detalle 2026-06'!D2:D784,'Detalle 2026-06'!G2:G784,"500 a 2.000 USD")/SUMIFS('Detalle 2026-06'!C2:C784,'Detalle 2026-06'!G2:G784,"500 a 2.000 USD"),"") -> 0.93446329
A9: Más de 2.000 USD | B9: =COUNTIFS('Detalle 2026-06'!C2:C784,">0",'Detalle 2026-06'!G2:G784,"Más de 2.000 USD") -> 5 | C9: =COUNTIFS('Detalle 2026-06'!C2:C784,">0",'Detalle 2026-06'!D2:D784,"<=0",'Detalle 2026-06'!G2:G784,"Más de 2.000 USD") -> 0 | D9: =IFERROR(COUNTIFS('Detalle 2026-06'!C2:C784,">0",'Detalle 2026-06'!D2:D784,"<=0",'Detalle 2026-06'!G2:G784,"Más de 2.000 USD")/COUNTIFS('Detalle 2026-06'!C2:C784,">0",'Detalle 2026-06'!G2:G784,"Más de 2.000 USD"),"") -> 0 | E9: =IFERROR(SUMIFS('Detalle 2026-06'!H2:H784,'Detalle 2026-06'!G2:G784,"Más de 2.000 USD")/SUMIFS('Detalle 2026-06'!C2:C784,'Detalle 2026-06'!G2:G784,"Más de 2.000 USD"),"") -> 0.99479938 | F9: =IFERROR(SUMIFS('Detalle 2026-06'!D2:D784,'Detalle 2026-06'!G2:G784,"Más de 2.000 USD")/SUMIFS('Detalle 2026-06'!C2:C784,'Detalle 2026-06'!G2:G784,"Más de 2.000 USD"),"") -> 1.281245
A10: Total México | B10: =COUNTIFS('Detalle 2026-06'!C2:C784,">0") -> 347 | C10: =COUNTIFS('Detalle 2026-06'!C2:C784,">0",'Detalle 2026-06'!D2:D784,"<=0") -> 86 | D10: =IFERROR(COUNTIFS('Detalle 2026-06'!C2:C784,">0",'Detalle 2026-06'!D2:D784,"<=0")/COUNTIFS('Detalle 2026-06'!C2:C784,">0"),"") -> 0.24783862 | E10: =IFERROR(SUM('Detalle 2026-06'!H2:H784)/SUM('Detalle 2026-06'!C2:C784),"") -> 0.76716609 | F10: =IFERROR(SUM('Detalle 2026-06'!D2:D784)/SUM('Detalle 2026-06'!C2:C784),"") -> 0.97602044

Sheet MRR Conglomerado
A1: Conglomerado | B1: Empresa(s) (Cliente) | C1: N° RUTs | D1: Filas en MRR_a_junio_26 (Moneda Loca v2) | E1: 2023-01 | F1: 2023-02 | G1: 2023-03 | H1: 2023-04 | I1: 2023-05 | J1: 2023-06 | K1: 2023-07 | L1: 2023-08 | M1: 2023-09 | N1: 2023-10 | O1: 2023-11 | P1: 2023-12 | Q1: 2024-01 | R1: 2024-02 | S1: 2024-03 | T1: 2024-04 | U1: 2024-05 | V1: 2024-06 | W1: 2024-07 | X1: 2024-08 | Y1: 2024-09 | Z1: 2024-10 | AA1: 2024-11 | AB1: 2024-12 | AC1: 2025-01 | AD1: 2025-02 | AE1: 2025-03 | AF1: 2025-04 | AG1: 2025-05 | AH1: 2025-06 | AI1: 2025-07 | AJ1: 2025-08 | AK1: 2025-09 | AL1: 2025-10 | AM1: 2025-11 | AN1: 2025-12 | AO1: 2026-01 | AP1: 2026-02 | AQ1: 2026-03 | AR1: 2026-04 | AS1: 2026-05 | AT1: 2026-06
A2: 180719670 | B2: SERVICIOS DE ADMINISTRACION GARFLO S.C. | C2: 1 | D2: 10780 | E2: 0 | F2: 0 | G2: 0 | H2: 0 | I2: 0 | J2: 0 | K2: 0 | L2: 0 | M2: 0 | N2: 0 | O2: 0 | P2: 0 | Q2: 0 | R2: 0 | S2: 0 | T2: 0 | U2: 0 | V2: 0 | W2: 0 | X2: 0 | Y2: 0 | Z2: 0 | AA2: 0 | AB2: 0 | AC2: 0 | AD2: 0 | AE2: 0 | AF2: 0 | AG2: 0 | AH2: 0 | AI2: 0 | AJ2: 0 | AK2: 0 | AL2: 0 | AM2: 0 | AN2: 0 | AO2: 0 | AP2: 0 | AQ2: 0 | AR2: 0 | AS2: 0 | AT2: 0
A3: 20602200958 | B3: VISMA ENTERPRISE SAC | C3: 1 | D3: 10781 | E3: 0 | F3: 0 | G3: 0 | H3: 0 | I3: 0 | J3: 0 | K3: 0 | L3: 0 | M3: 0 | N3: 0 | O3: 0 | P3: 0 | Q3: 0 | R3: 0 | S3: 0 | T3: 0 | U3: 0 | V3: 0 | W3: 0 | X3: 0 | Y3: 0 | Z3: 0 | AA3: 0 | AB3: 0 | AC3: 0 | AD3: 2689.0194 | AE3: 2311.0466 | AF3: 2390.718 | AG3: 2641.8962 | AH3: 2445.6075 | AI3: 2295.1137 | AJ3: 2717.1934 | AK3: 4154.0418 | AL3: 4511.3294 | AM3: 4642.3224 | AN3: 4396.9168 | AO3: 4087.9962 | AP3: 4119.0072 | AQ3: 4477.211 | AR3: 4187.0678 | AS3: 4104.4761 | AT3: 4573.1681
A4: 24082020 | B4: BANKAYA SAPI DE CV | C4: 1 | D4: 10782 | E4: 0 | F4: 0 | G4: 0 | H4: 0 | I4: 0 | J4: 0 | K4: 0 | L4: -13096.79 | M4: 0 | N4: 0 | O4: 0 | P4: 0 | Q4: 0 | R4: 0 | S4: 0 | T4: 0 | U4: 0 | V4: 0 | W4: 0 | X4: 0 | Y4: 0 | Z4: 0 | AA4: 0 | AB4: 0 | AC4: 0 | AD4: 0 | AE4: 0 | AF4: 0 | AG4: 0 | AH4: 0 | AI4: 0 | AJ4: 0 | AK4: 0 | AL4: 0 | AM4: 0 | AN4: 0 | AO4: 0 | AP4: 0 | AQ4: 0 | AR4: 0 | AS4: 0 | AT4: 0
A5: AAAG8010092 | B5: GIORDANO AYALA ARIAS | C5: 1 | D5: 10783 | E5: 0 | F5: 0 | G5: 0 | H5: 0 | I5: 0 | J5: 0 | K5: 0 | L5: 0 | M5: 0 | N5: 0 | O5: 0 | P5: 0 | Q5: 0 | R5: 0 | S5: 0 | T5: 0 | U5: 0 | V5: 0 | W5: 0 | X5: 0 | Y5: 0 | Z5: 0 | AA5: 0 | AB5: 0 | AC5: 0 | AD5: 0 | AE5: 0 | AF5: 0 | AG5: 0 | AH5: 0 | AI5: 0 | AJ5: 0 | AK5: 0 | AL5: 182.33919 | AM5: 182.3324 | AN5: 182.35066 | AO5: 0 | AP5: 226.9164 | AQ5: 416.10575 | AR5: 415.93505 | AS5: 264.66531 | AT5: 113.41037
A6: AAAL6611248 | B6: LETICIA ALMAZAN ARELLANO | C6: 1 | D6: 10784 | E6: 0 | F6: 0 | G6: 0 | H6: 0 | I6: 0 | J6: 0 | K6: 0 | L6: 0 | M6: 0 | N6: 0 | O6: 0 | P6: 0 | Q6: 0 | R6: 0 | S6: 0 | T6: 0 | U6: 0 | V6: 0 | W6: 0 | X6: 0 | Y6: 0 | Z6: 0 | AA6: 0 | AB6: 0 | AC6: 0 | AD6: 0 | AE6: 0 | AF6: 0 | AG6: 0 | AH6: 0 | AI6: 0 | AJ6: 1150.0263 | AK6: 1299.9267 | AL6: 1150.0262 | AM6: 1100.0477 | AN6: 1100.0385 | AO6: 1036.8256 | AP6: 1088.681 | AQ6: 1088.6109 | AR6: 1088.6938 | AS6: 1088.607 | AT6: 1088.5995
A7: AAG160805FE | B7: ABASTECEDORA AGRICENTER | C7: 1 | D7: 10785 | E7: 0 | F7: 0 | G7: 0 | H7: 0 | I7: 0 | J7: 0 | K7: 0 | L7: 0 | M7: 0 | N7: 0 | O7: 0 | P7: 0 | Q7: 0 | R7: 0 | S7: 0 | T7: 0 | U7: 0 | V7: 0 | W7: 0 | X7: 0 | Y7: 2870.0292 | Z7: 2834.9619 | AA7: 2975.0199 | AB7: 2869.9868 | AC7: 2990.5348 | AD7: 2990.6051 | AE7: 2881.1538 | AF7: 2881.197 | AG7: 2844.7182 | AH7: 2844.6476 | AI7: 2881.2042 | AJ7: 2881.2166 | AK7: 2698.733 | AL7: 2552.9328 | AM7: 2552.8371 | AN7: 2443.5708 | AO7: 2533.9646 | AP7: 2647.4155 | AQ7: 2571.7798 | AR7: 2571.7452 | AS7: 2458.3236 | AT7: 2458.2747
A8: AAGA570212I | B8: ARTURO ALMARAZ GARCIA | C8: 1 | D8: 10786 | E8: 0 | F8: 0 | G8: 0 | H8: 0 | I8: 0 | J8: 0 | K8: 749.9767 | L8: 750.05782 | M8: 750.00757 | N8: 749.99438 | O8: 749.92028 | P8: 749.98824 | Q8: 787.55579 | R8: 787.5344 | S8: 787.4932 | T8: 787.53024 | U8: 787.57368 | V8: 787.42466 | W8: 787.5168 | X8: 787.44136 | Y8: 787.496 | Z8: 787.02166 | AA8: 787.58331 | AB8: 787.56177 | AC8: 0 | AD8: 0 | AE8: 562.75884 | AF8: 562.7292 | AG8: 562.72968 | AH8: 562.773 | AI8: 0 | AJ8: 0 | AK8: 0 | AL8: 0 | AM8: 0 | AN8: 0 | AO8: 0 | AP8: 0 | AQ8: 0 | AR8: 0 | AS8: 0 | AT8: 0
A9: AAM970602V7 | B9: ANALISIS AMBIENTAL | C9: 1 | D9: 10787 | E9: 0 | F9: 0 | G9: 0 | H9: 0 | I9: 0 | J9: 0 | K9: 0 | L9: 0 | M9: 0 | N9: 0 | O9: 0 | P9: 0 | Q9: 0 | R9: 0 | S9: 0 | T9: 0 | U9: 0 | V9: 0 | W9: 0 | X9: 0 | Y9: 0 | Z9: 0 | AA9: 0 | AB9: 0 | AC9: 0 | AD9: 0 | AE9: 0 | AF9: 0 | AG9: 0 | AH9: 0 | AI9: 0 | AJ9: 0 | AK9: 0 | AL9: 0 | AM9: 0 | AN9: 0 | AO9: 0 | AP9: 1920.0751 | AQ9: 1855.9983 | AR9: 1856.0071 | AS9: 1855.946 | AT9: 1856.0447
A10: AAR160311AL | B10: ALIMENTOS AREM | C10: 1 | D10: 10788 | E10: 6574.1712 | F10: 6574.1448 | G10: 6231.7523 | H10: 6094.7356 | I10: 6300.181 | J10: 6163.1298 | K10: 6163.193 | L10: 7327.4235 | M10: 6985.0294 | N10: 6916.5345 | O10: 6711.081 | P10: 6300.2057 | Q10: 13148.078 | R10: 6437.2006 | S10: 6710.9771 | T10: 6505.5514 | U10: 5752.2551 | V10: 6163.2469 | W10: 6505.6388 | X10: 5889.2523 | Y10: 6094.6284 | Z10: 6231.6239 | AA10: 6026.1654 | AB10: 5889.3108 | AC10: 6136.9968 | AD10: 6493.8443 | AE10: 6422.4317 | AF10: 6565.174 | AG10: 6850.597 | AH10: 6850.5337 | AI10: 6779.138 | AJ10: 6707.8033 | AK10: 6921.9354 | AL10: 6993.3526 | AM10: 7064.5551 | AN10: 6779.1646 | AO10: 7472.9371 | AP10: 7843.0246 | AQ10: 7546.9416 | AR10: 7768.9158 | AS10: 7103.0354 | AT10: 7177.0561
A11: AARG6801036 | B11: GERARDO FILADELFO ALVAREZ ROSAS | C11: 1 | D11: 10789 | E11: 0 | F11: 0 | G11: 0 | H11: 0 | I11: 0 | J11: 0 | K11: 1824.0421 | L11: 2279.9815 | M11: 2279.9878 | N11: 2279.9757 | O11: 2280.0467 | P11: 2280.0793 | Q11: 2280.083 | R11: 2280.0377 | S11: 2279.9425 | T11: 2393.9149 | U11: 2393.9188 | V11: 2393.9626 | W11: 2394.0511 | X11: 2394.0518 | Y11: 2393.9878 | Z11: 2393.9411 | AA11: 2393.9757 | AB11: 2394.0502 | AC11: 0 | AD11: 2394.0033 | AE11: 0 | AF11: 0 | AG11: 0 | AH11: 0 | AI11: 0 | AJ11: 0 | AK11: 0 | AL11: 0 | AM11: 0 | AN11: 0 | AO11: 0 | AP11: 0 | AQ11: 0 | AR11: 0 | AS11: 0 | AT11: 0
A12: AARG680103H | B12: GERARDO FILADELFO ALVAREZ ROSAS | C12: 1 | D12: 10790 | E12: 0 | F12: 0 | G12: 0 | H12: 0 | I12: 0 | J12: 2250.0179 | K12: 0 | L12: 0 | M12: 0 | N12: 0 | O12: 0 | P12: 0 | Q12: 0 | R12: 0 | S12: 0 | T12: 0 | U12: 0 | V12: 0 | W12: 0 | X12: 0 | Y12: 0 | Z12: 0 | AA12: 0 | AB12: 0 | AC12: 0 | AD12: 0 | AE12: 0 | AF12: 0 | AG12: 0 | AH12: 0 | AI12: 0 | AJ12: 0 | AK12: 0 | AL12: 0 | AM12: 0 | AN12: 0 | AO12: 0 | AP12: 0 | AQ12: 0 | AR12: 0 | AS12: 0 | AT12: 0
A13: AAS9610021I | B13: ANCORA AGENTE DE SEGUROS Y DE FIANZAS | C13: 1 | D13: 10791 | E13: 0 | F13: 0 | G13: 0 | H13: 0 | I13: 0 | J13: 0 | K13: 0 | L13: 0 | M13: 0 | N13: 0 | O13: 0 | P13: 0 | Q13: 0 | R13: 0 | S13: 0 | T13: 0 | U13: 0 | V13: 0 | W13: 0 | X13: 0 | Y13: 0 | Z13: 0 | AA13: 0 | AB13: 0 | AC13: 0 | AD13: 0 | AE13: 0 | AF13: 0 | AG13: 0 | AH13: 0 | AI13: 0 | AJ13: 0 | AK13: 0 | AL13: 0 | AM13: 0 | AN13: 0 | AO13: 0 | AP13: 0 | AQ13: 0 | AR13: 0 | AS13: 0 | AT13: 8449.9475
... A784: ZSU920314FC | B784: ZAPATERIAS SUPER | C784: 1 | D784: 11562 | E784: 0 | F784: 0 | G784: 0 | H784: 0 | I784: 0 | J784: 0 | K784: 0 | L784: 0 | M784: 0 | N784: 0 | O784: 0 | P784: 0 | Q784: 0 | R784: 0 | S784: 0 | T784: 0 | U784: 0 | V784: 0 | W784: 7199.9661 | X784: 7200.0021 | Y784: 7200.0759 | Z784: 7200.0655 | AA784: 7200.0911 | AB784: 7199.9577 | AC784: 7199.9488 | AD784: 7200.0763 | AE784: 7199.9248 | AF784: 7199.9576 | AG784: 7200.0838 | AH784: 7199.9062 | AI784: 5363.9119 | AJ784: 4859.9329 | AK784: 5147.9739 | AL784: 5327.988 | AM784: 5471.9898 | AN784: 5616.0048 | AO784: 5898.2172 | AP784: 5972.8193 | AQ784: 0 | AR784: 0 | AS784: 0 | AT784: 0

Sheet Detalle 2026-06
A1: Conglomerado | B1: TC MXN/USD mes base (sólo tamaño) | C1: MRR 2025-06 MXN (base) | D1: MRR 2026-06 MXN (actual) | E1: NRR (MXN) | F1: Tamaño USD (base/TC) | G1: Segmento | H1: MRR retenido MXN (=MIN(actual;base))
A2: 180719670 | B2: 18.885 | C2: =IF('MRR Conglomerado'!AH2>0,'MRR Conglomerado'!AH2,"") | D2: =IF(C2="","",'MRR Conglomerado'!AT2) | E2: =IF(C2="","",D2/C2) | F2: =IF(C2="","",C2/B2) | G2: =IF(F2="","",IF(F2<100,"Menos de 100 USD",IF(F2<500,"100 a 500 USD",IF(F2<2000,"500 a 2.000 USD","Más de 2.000 USD")))) | H2: =IF(C2="","",MIN(D2,C2))
A3: 20602200958 | B3: 18.885 | C3: =IF('MRR Conglomerado'!AH3>0,'MRR Conglomerado'!AH3,"") -> 2445.6075 | D3: =IF(C3="","",'MRR Conglomerado'!AT3) -> 4573.1681 | E3: =IF(C3="","",D3/C3) -> 1.8699518 | F3: =IF(C3="","",C3/B3) -> 129.5 | G3: =IF(F3="","",IF(F3<100,"Menos de 100 USD",IF(F3<500,"100 a 500 USD",IF(F3<2000,"500 a 2.000 USD","Más de 2.000 USD")))) -> 100 a 500 USD | H3: =IF(C3="","",MIN(D3,C3)) -> 2445.6075
A4: 24082020 | B4: 18.885 | C4: =IF('MRR Conglomerado'!AH4>0,'MRR Conglomerado'!AH4,"") | D4: =IF(C4="","",'MRR Conglomerado'!AT4) | E4: =IF(C4="","",D4/C4) | F4: =IF(C4="","",C4/B4) | G4: =IF(F4="","",IF(F4<100,"Menos de 100 USD",IF(F4<500,"100 a 500 USD",IF(F4<2000,"500 a 2.000 USD","Más de 2.000 USD")))) | H4: =IF(C4="","",MIN(D4,C4))
A5: AAAG8010092 | B5: 18.885 | C5: =IF('MRR Conglomerado'!AH5>0,'MRR Conglomerado'!AH5,"") | D5: =IF(C5="","",'MRR Conglomerado'!AT5) | E5: =IF(C5="","",D5/C5) | F5: =IF(C5="","",C5/B5) | G5: =IF(F5="","",IF(F5<100,"Menos de 100 USD",IF(F5<500,"100 a 500 USD",IF(F5<2000,"500 a 2.000 USD","Más de 2.000 USD")))) | H5: =IF(C5="","",MIN(D5,C5))
A6: AAAL6611248 | B6: 18.885 | C6: =IF('MRR Conglomerado'!AH6>0,'MRR Conglomerado'!AH6,"") | D6: =IF(C6="","",'MRR Conglomerado'!AT6) | E6: =IF(C6="","",D6/C6) | F6: =IF(C6="","",C6/B6) | G6: =IF(F6="","",IF(F6<100,"Menos de 100 USD",IF(F6<500,"100 a 500 USD",IF(F6<2000,"500 a 2.000 USD","Más de 2.000 USD")))) | H6: =IF(C6="","",MIN(D6,C6))
A7: AAG160805FE | B7: 18.885 | C7: =IF('MRR Conglomerado'!AH7>0,'MRR Conglomerado'!AH7,"") -> 2844.6476 | D7: =IF(C7="","",'MRR Conglomerado'!AT7) -> 2458.2747 | E7: =IF(C7="","",D7/C7) -> 0.86417551 | F7: =IF(C7="","",C7/B7) -> 150.63 | G7: =IF(F7="","",IF(F7<100,"Menos de 100 USD",IF(F7<500,"100 a 500 USD",IF(F7<2000,"500 a 2.000 USD","Más de 2.000 USD")))) -> 100 a 500 USD | H7: =IF(C7="","",MIN(D7,C7)) -> 2458.2747
A8: AAGA570212I | B8: 18.885 | C8: =IF('MRR Conglomerado'!AH8>0,'MRR Conglomerado'!AH8,"") -> 562.773 | D8: =IF(C8="","",'MRR Conglomerado'!AT8) -> 0 | E8: =IF(C8="","",D8/C8) -> 0 | F8: =IF(C8="","",C8/B8) -> 29.8 | G8: =IF(F8="","",IF(F8<100,"Menos de 100 USD",IF(F8<500,"100 a 500 USD",IF(F8<2000,"500 a 2.000 USD","Más de 2.000 USD")))) -> Menos de 100 USD | H8: =IF(C8="","",MIN(D8,C8)) -> 0
A9: AAM970602V7 | B9: 18.885 | C9: =IF('MRR Conglomerado'!AH9>0,'MRR Conglomerado'!AH9,"") | D9: =IF(C9="","",'MRR Conglomerado'!AT9) | E9: =IF(C9="","",D9/C9) | F9: =IF(C9="","",C9/B9) | G9: =IF(F9="","",IF(F9<100,"Menos de 100 USD",IF(F9<500,"100 a 500 USD",IF(F9<2000,"500 a 2.000 USD","Más de 2.000 USD")))) | H9: =IF(C9="","",MIN(D9,C9))
A10: AAR160311AL | B10: 18.885 | C10: =IF('MRR Conglomerado'!AH10>0,'MRR Conglomerado'!AH10,"") -> 6850.5337 | D10: =IF(C10="","",'MRR Conglomerado'!AT10) -> 7177.0561 | E10: =IF(C10="","",D10/C10) -> 1.0476638 | F10: =IF(C10="","",C10/B10) -> 362.75 | G10: =IF(F10="","",IF(F10<100,"Menos de 100 USD",IF(F10<500,"100 a 500 USD",IF(F10<2000,"500 a 2.000 USD","Más de 2.000 USD")))) -> 100 a 500 USD | H10: =IF(C10="","",MIN(D10,C10)) -> 6850.5337
A11: AARG6801036 | B11: 18.885 | C11: =IF('MRR Conglomerado'!AH11>0,'MRR Conglomerado'!AH11,"") | D11: =IF(C11="","",'MRR Conglomerado'!AT11) | E11: =IF(C11="","",D11/C11) | F11: =IF(C11="","",C11/B11) | G11: =IF(F11="","",IF(F11<100,"Menos de 100 USD",IF(F11<500,"100 a 500 USD",IF(F11<2000,"500 a 2.000 USD","Más de 2.000 USD")))) | H11: =IF(C11="","",MIN(D11,C11))
A12: AARG680103H | B12: 18.885 | C12: =IF('MRR Conglomerado'!AH12>0,'MRR Conglomerado'!AH12,"") | D12: =IF(C12="","",'MRR Conglomerado'!AT12) | E12: =IF(C12="","",D12/C12) | F12: =IF(C12="","",C12/B12) | G12: =IF(F12="","",IF(F12<100,"Menos de 100 USD",IF(F12<500,"100 a 500 USD",IF(F12<2000,"500 a 2.000 USD","Más de 2.000 USD")))) | H12: =IF(C12="","",MIN(D12,C12))
A13: AAS9610021I | B13: 18.885 | C13: =IF('MRR Conglomerado'!AH13>0,'MRR Conglomerado'!AH13,"") | D13: =IF(C13="","",'MRR Conglomerado'!AT13) | E13: =IF(C13="","",D13/C13) | F13: =IF(C13="","",C13/B13) | G13: =IF(F13="","",IF(F13<100,"Menos de 100 USD",IF(F13<500,"100 a 500 USD",IF(F13<2000,"500 a 2.000 USD","Más de 2.000 USD")))) | H13: =IF(C13="","",MIN(D13,C13))
... A784: ZSU920314FC | B784: 18.885 | C784: =IF('MRR Conglomerado'!AH784>0,'MRR Conglomerado'!AH784,"") -> 7199.9062 | D784: =IF(C784="","",'MRR Conglomerado'!AT784) -> 0 | E784: =IF(C784="","",D784/C784) -> 0 | F784: =IF(C784="","",C784/B784) -> 381.25 | G784: =IF(F784="","",IF(F784<100,"Menos de 100 USD",IF(F784<500,"100 a 500 USD",IF(F784<2000,"500 a 2.000 USD","Más de 2.000 USD")))) -> 100 a 500 USD | H784: =IF(C784="","",MIN(D784,C784)) -> 0

Sheet Detalle Fuga 2026-06
A1: Conglomerado | B1: Empresa(s) | C1: MRR jun-2025 MXN (perdido) | D1: Tamaño USD | E1: Segmento | F1: Último mes con MRR | G1: Meses con MRR (vida) | H1: MRR jun-2026 (verificación) | J1: TC MXN/USD jun-25: | K1: 18.885
A2: ='MRR Conglomerado'!A61 -> ATE100413UD | B2: ='MRR Conglomerado'!B61 -> ALIADOS EN TECNOLOGIA | C2: ='MRR Conglomerado'!AH61 -> 25999.924 | D2: =C2/$K$1 -> 1376.75 | E2: =IF(D2<100,"Menos de 100 USD",IF(D2<500,"100 a 500 USD",IF(D2<2000,"500 a 2.000 USD","Más de 2.000 USD"))) -> 500 a 2.000 USD | F2: =LOOKUP(2,1/('MRR Conglomerado'!E61:AT61>0),'MRR Conglomerado'!$E$1:$AT$1) -> 2025-09 | G2: =COUNTIF('MRR Conglomerado'!E61:AT61,">0") -> 4 | H2: ='MRR Conglomerado'!AT61 -> 0
A3: ='MRR Conglomerado'!A238 -> EHM910503BW | B3: ='MRR Conglomerado'!B238 -> EQUIPOS HIDROMECANICOS MC | C3: ='MRR Conglomerado'!AH238 -> 15678.516 | D3: =C3/$K$1 -> 830.21 | E3: =IF(D3<100,"Menos de 100 USD",IF(D3<500,"100 a 500 USD",IF(D3<2000,"500 a 2.000 USD","Más de 2.000 USD"))) -> 500 a 2.000 USD | F3: =LOOKUP(2,1/('MRR Conglomerado'!E238:AT238>0),'MRR Conglomerado'!$E$1:$AT$1) -> 2025-11 | G3: =COUNTIF('MRR Conglomerado'!E238:AT238,">0") -> 35 | H3: ='MRR Conglomerado'!AT238 -> 0
A4: ='MRR Conglomerado'!A497 -> MSP981215H4 | B4: ='MRR Conglomerado'!B497 -> MERCURIO SEGURIDAD PRIVADA | C4: ='MRR Conglomerado'!AH497 -> 15361.437 | D4: =C4/$K$1 -> 813.42 | E4: =IF(D4<100,"Menos de 100 USD",IF(D4<500,"100 a 500 USD",IF(D4<2000,"500 a 2.000 USD","Más de 2.000 USD"))) -> 500 a 2.000 USD | F4: =LOOKUP(2,1/('MRR Conglomerado'!E497:AT497>0),'MRR Conglomerado'!$E$1:$AT$1) -> 2025-10 | G4: =COUNTIF('MRR Conglomerado'!E497:AT497,">0") -> 8 | H4: ='MRR Conglomerado'!AT497 -> 0
A5: ='MRR Conglomerado'!A570 -> PLO2310139T | B5: ='MRR Conglomerado'!B570 -> PROXIMIDAD Y LOGISTICA | C5: ='MRR Conglomerado'!AH570 -> 15023.017 | D5: =C5/$K$1 -> 795.5 | E5: =IF(D5<100,"Menos de 100 USD",IF(D5<500,"100 a 500 USD",IF(D5<2000,"500 a 2.000 USD","Más de 2.000 USD"))) -> 500 a 2.000 USD | F5: =LOOKUP(2,1/('MRR Conglomerado'!E570:AT570>0),'MRR Conglomerado'!$E$1:$AT$1) -> 2025-10 | G5: =COUNTIF('MRR Conglomerado'!E570:AT570,">0") -> 22 | H5: ='MRR Conglomerado'!AT570 -> 0
A6: ='MRR Conglomerado'!A699 -> TAD140205H9 | B6: ='MRR Conglomerado'!B699 -> TIENDAS ADITIVO | C6: ='MRR Conglomerado'!AH699 -> 12297.723 | D6: =C6/$K$1 -> 651.19 | E6: =IF(D6<100,"Menos de 100 USD",IF(D6<500,"100 a 500 USD",IF(D6<2000,"500 a 2.000 USD","Más de 2.000 USD"))) -> 500 a 2.000 USD | F6: =LOOKUP(2,1/('MRR Conglomerado'!E699:AT699>0),'MRR Conglomerado'!$E$1:$AT$1) -> 2026-05 | G6: =COUNTIF('MRR Conglomerado'!E699:AT699,">0") -> 41 | H6: ='MRR Conglomerado'!AT699 -> 0
A7: ='MRR Conglomerado'!A311 -> GCA6601031M | B7: ='MRR Conglomerado'!B311 -> GRUPO COMERCIAL ATLAS | C7: ='MRR Conglomerado'!AH311 -> 11393.32 | D7: =C7/$K$1 -> 603.3 | E7: =IF(D7<100,"Menos de 100 USD",IF(D7<500,"100 a 500 USD",IF(D7<2000,"500 a 2.000 USD","Más de 2.000 USD"))) -> 500 a 2.000 USD | F7: =LOOKUP(2,1/('MRR Conglomerado'!E311:AT311>0),'MRR Conglomerado'!$E$1:$AT$1) -> 2025-10 | G7: =COUNTIF('MRR Conglomerado'!E311:AT311,">0") -> 34 | H7: ='MRR Conglomerado'!AT311 -> 0
A8: ='MRR Conglomerado'!A415 -> ITM100309S9 | B8: ='MRR Conglomerado'!B415 -> INSTALACIONES DE TELECOMUNICACIONES DE MEXICO | C8: ='MRR Conglomerado'!AH415 -> 11280.011 | D8: =C8/$K$1 -> 597.3 | E8: =IF(D8<100,"Menos de 100 USD",IF(D8<500,"100 a 500 USD",IF(D8<2000,"500 a 2.000 USD","Más de 2.000 USD"))) -> 500 a 2.000 USD | F8: =LOOKUP(2,1/('MRR Conglomerado'!E415:AT415>0),'MRR Conglomerado'!$E$1:$AT$1) -> 2025-10 | G8: =COUNTIF('MRR Conglomerado'!E415:AT415,">0") -> 6 | H8: ='MRR Conglomerado'!AT415 -> 0
A9: ='MRR Conglomerado'!A140 -> CIC991005MS | B9: ='MRR Conglomerado'!B140 -> CONSTRUCTORA E INMOBILIARIA CAROME | C9: ='MRR Conglomerado'!AH140 -> 9846.8278 | D9: =C9/$K$1 -> 521.41 | E9: =IF(D9<100,"Menos de 100 USD",IF(D9<500,"100 a 500 USD",IF(D9<2000,"500 a 2.000 USD","Más de 2.000 USD"))) -> 500 a 2.000 USD | F9: =LOOKUP(2,1/('MRR Conglomerado'!E140:AT140>0),'MRR Conglomerado'!$E$1:$AT$1) -> 2026-01 | G9: =COUNTIF('MRR Conglomerado'!E140:AT140,">0") -> 19 | H9: ='MRR Conglomerado'!AT140 -> 0
A10: ='MRR Conglomerado'!A317 -> GCP831026IG | B10: ='MRR Conglomerado'!B317 -> GRAN CAFE DE LA PARROQUIA DE VERACRUZ | C10: ='MRR Conglomerado'!AH317 -> 9460.0631 | D10: =C10/$K$1 -> 500.93 | E10: =IF(D10<100,"Menos de 100 USD",IF(D10<500,"100 a 500 USD",IF(D10<2000,"500 a 2.000 USD","Más de 2.000 USD"))) -> 500 a 2.000 USD | F10: =LOOKUP(2,1/('MRR Conglomerado'!E317:AT317>0),'MRR Conglomerado'!$E$1:$AT$1) -> 2025-07 | G10: =COUNTIF('MRR Conglomerado'!E317:AT317,">0") -> 12 | H10: ='MRR Conglomerado'!AT317 -> 0
A11: ='MRR Conglomerado'!A563 -> PIM88041917 | B11: ='MRR Conglomerado'!B563 -> PLASTICOS INDUSTRIALES DE MONTERREY | C11: ='MRR Conglomerado'!AH563 -> 9192.0849 | D11: =C11/$K$1 -> 486.74 | E11: =IF(D11<100,"Menos de 100 USD",IF(D11<500,"100 a 500 USD",IF(D11<2000,"500 a 2.000 USD","Más de 2.000 USD"))) -> 100 a 500 USD | F11: =LOOKUP(2,1/('MRR Conglomerado'!E563:AT563>0),'MRR Conglomerado'!$E$1:$AT$1) -> 2026-05 | G11: =COUNTIF('MRR Conglomerado'!E563:AT563,">0") -> 29 | H11: ='MRR Conglomerado'!AT563 -> 0
A12: ='MRR Conglomerado'!A761 -> VJU981123KB | B12: ='MRR Conglomerado'!B761 -> VILLAGOMEZ JURADO | C12: ='MRR Conglomerado'!AH761 -> 9108.0467 | D12: =C12/$K$1 -> 482.29 | E12: =IF(D12<100,"Menos de 100 USD",IF(D12<500,"100 a 500 USD",IF(D12<2000,"500 a 2.000 USD","Más de 2.000 USD"))) -> 100 a 500 USD | F12: =LOOKUP(2,1/('MRR Conglomerado'!E761:AT761>0),'MRR Conglomerado'!$E$1:$AT$1) -> 2026-04 | G12: =COUNTIF('MRR Conglomerado'!E761:AT761,">0") -> 36 | H12: ='MRR Conglomerado'!AT761 -> 0
A13: ='MRR Conglomerado'!A630 -> RTD220308U2 | B13: ='MRR Conglomerado'!B630 -> RM TEAM 2022 | C13: ='MRR Conglomerado'!AH630 -> 8693.1432 | D13: =C13/$K$1 -> 460.32 | E13: =IF(D13<100,"Menos de 100 USD",IF(D13<500,"100 a 500 USD",IF(D13<2000,"500 a 2.000 USD","Más de 2.000 USD"))) -> 100 a 500 USD | F13: =LOOKUP(2,1/('MRR Conglomerado'!E630:AT630>0),'MRR Conglomerado'!$E$1:$AT$1) -> 2025-08 | G13: =COUNTIF('MRR Conglomerado'!E630:AT630,">0") -> 32 | H13: ='MRR Conglomerado'!AT630 -> 0
A14: ='MRR Conglomerado'!A682 -> SNO0202153Z | B14: ='MRR Conglomerado'!B682 -> SIMILARES DEL NORESTE | C14: ='MRR Conglomerado'!AH682 -> 8449.7156 | D14: =C14/$K$1 -> 447.43 | E14: =IF(D14<100,"Menos de 100 USD",IF(D14<500,"100 a 500 USD",IF(D14<2000,"500 a 2.000 USD","Más de 2.000 USD"))) -> 100 a 500 USD | F14: =LOOKUP(2,1/('MRR Conglomerado'!E682:AT682>0),'MRR Conglomerado'!$E$1:$AT$1) -> 2025-10 | G14: =COUNTIF('MRR Conglomerado'!E682:AT682,">0") -> 12 | H14: ='MRR Conglomerado'!AT682 -> 0
A15: ='MRR Conglomerado'!A572 -> PLT7910247B | B15: ='MRR Conglomerado'!B572 -> PRODUCTOS LOL TUN | C15: ='MRR Conglomerado'!AH572 -> 8161.7193 | D15: =C15/$K$1 -> 432.18 | E15: =IF(D15<100,"Menos de 100 USD",IF(D15<500,"100 a 500 USD",IF(D15<2000,"500 a 2.000 USD","Más de 2.000 USD"))) -> 100 a 500 USD | F15: =LOOKUP(2,1/('MRR Conglomerado'!E572:AT572>0),'MRR Conglomerado'!$E$1:$AT$1) -> 2025-12 | G15: =COUNTIF('MRR Conglomerado'!E572:AT572,">0") -> 36 | H15: ='MRR Conglomerado'!AT572 -> 0
A16: ='MRR Conglomerado'!A43 -> ALO0508239T | B16: ='MRR Conglomerado'!B43 -> ABC LOGISTICA | C16: ='MRR Conglomerado'!AH43 -> 7337.0113 | D16: =C16/$K$1 -> 388.51 | E16: =IF(D16<100,"Menos de 100 USD",IF(D16<500,"100 a 500 USD",IF(D16<2000,"500 a 2.000 USD","Más de 2.000 USD"))) -> 100 a 500 USD | F16: =LOOKUP(2,1/('MRR Conglomerado'!E43:AT43>0),'MRR Conglomerado'!$E$1:$AT$1) -> 2025-06 | G16: =COUNTIF('MRR Conglomerado'!E43:AT43,">0") -> 8 | H16: ='MRR Conglomerado'!AT43 -> 0
A17: ='MRR Conglomerado'!A784 -> ZSU920314FC | B17: ='MRR Conglomerado'!B784 -> ZAPATERIAS SUPER | C17: ='MRR Conglomerado'!AH784 -> 7199.9062 | D17: =C17/$K$1 -> 381.25 | E17: =IF(D17<100,"Menos de 100 USD",IF(D17<500,"100 a 500 USD",IF(D17<2000,"500 a 2.000 USD","Más de 2.000 USD"))) -> 100 a 500 USD | F17: =LOOKUP(2,1/('MRR Conglomerado'!E784:AT784>0),'MRR Conglomerado'!$E$1:$AT$1) -> 2026-02 | G17: =COUNTIF('MRR Conglomerado'!E784:AT784,">0") -> 20 | H17: ='MRR Conglomerado'!AT784 -> 0
A18: ='MRR Conglomerado'!A72 -> BAN191001Q6 | B18: ='MRR Conglomerado'!B72 -> BKAYA | C18: ='MRR Conglomerado'!AH72 -> 7091.3175 | D18: =C18/$K$1 -> 375.5 | E18: =IF(D18<100,"Menos de 100 USD",IF(D18<500,"100 a 500 USD",IF(D18<2000,"500 a 2.000 USD","Más de 2.000 USD"))) -> 100 a 500 USD | F18: =LOOKUP(2,1/('MRR Conglomerado'!E72:AT72>0),'MRR Conglomerado'!$E$1:$AT$1) -> 2026-04 | G18: =COUNTIF('MRR Conglomerado'!E72:AT72,">0") -> 36 | H18: ='MRR Conglomerado'!AT72 -> 0
A19: ='MRR Conglomerado'!A490 -> MRC210607EW | B19: ='MRR Conglomerado'!B490 -> MEDICA RISO CDMX | C19: ='MRR Conglomerado'!AH490 -> 6815.7854 | D19: =C19/$K$1 -> 360.91 | E19: =IF(D19<100,"Menos de 100 USD",IF(D19<500,"100 a 500 USD",IF(D19<2000,"500 a 2.000 USD","Más de 2.000 USD"))) -> 100 a 500 USD | F19: =LOOKUP(2,1/('MRR Conglomerado'!E490:AT490>0),'MRR Conglomerado'!$E$1:$AT$1) -> 2025-08 | G19: =COUNTIF('MRR Conglomerado'!E490:AT490,">0") -> 13 | H19: ='MRR Conglomerado'!AT490 -> 0
A20: ='MRR Conglomerado'!A111 -> CCL8603057Q | B20: ='MRR Conglomerado'!B111 -> CONFECCIONES CLABECK | C20: ='MRR Conglomerado'!AH111 -> 6196.5462 | D20: =C20/$K$1 -> 328.12 | E20: =IF(D20<100,"Menos de 100 USD",IF(D20<500,"100 a 500 USD",IF(D20<2000,"500 a 2.000 USD","Más de 2.000 USD"))) -> 100 a 500 USD | F20: =LOOKUP(2,1/('MRR Conglomerado'!E111:AT111>0),'MRR Conglomerado'!$E$1:$AT$1) -> 2025-08 | G20: =COUNTIF('MRR Conglomerado'!E111:AT111,">0") -> 12 | H20: ='MRR Conglomerado'!AT111 -> 0
A21: ='MRR Conglomerado'!A324 -> GED62010165 | B21: ='MRR Conglomerado'!B324 -> GOBIERNO DEL ESTADO DE DURANGO | C21: ='MRR Conglomerado'!AH324 -> 5876.6343 | D21: =C21/$K$1 -> 311.18 | E21: =IF(D21<100,"Menos de 100 USD",IF(D21<500,"100 a 500 USD",IF(D21<2000,"500 a 2.000 USD","Más de 2.000 USD"))) -> 100 a 500 USD | F21: =LOOKUP(2,1/('MRR Conglomerado'!E324:AT324>0),'MRR Conglomerado'!$E$1:$AT$1) -> 2026-03 | G21: =COUNTIF('MRR Conglomerado'!E324:AT324,">0") -> 34 | H21: ='MRR Conglomerado'!AT324 -> 0
A22: ='MRR Conglomerado'!A207 -> DMA150609DQ | B22: ='MRR Conglomerado'!B207 -> DESARROLLOS MAFERSA | C22: ='MRR Conglomerado'!AH207 -> 5856.0496 | D22: =C22/$K$1 -> 310.09 | E22: =IF(D22<100,"Menos de 100 USD",IF(D22<500,"100 a 500 USD",IF(D22<2000,"500 a 2.000 USD","Más de 2.000 USD"))) -> 100 a 500 USD | F22: =LOOKUP(2,1/('MRR Conglomerado'!E207:AT207>0),'MRR Conglomerado'!$E$1:$AT$1) -> 2025-11 | G22: =COUNTIF('MRR Conglomerado'!E207:AT207,">0") -> 6 | H22: ='MRR Conglomerado'!AT207 -> 0
A23: ='MRR Conglomerado'!A669 -> SIP050722BA | B23: ='MRR Conglomerado'!B669 -> SUMINISTROS INTEGRALES PANAMERICANOS | C23: ='MRR Conglomerado'!AH669 -> 5789.9522 | D23: =C23/$K$1 -> 306.59 | E23: =IF(D23<100,"Menos de 100 USD",IF(D23<500,"100 a 500 USD",IF(D23<2000,"500 a 2.000 USD","Más de 2.000 USD"))) -> 100 a 500 USD | F23: =LOOKUP(2,1/('MRR Conglomerado'!E669:AT669>0),'MRR Conglomerado'!$E$1:$AT$1) -> 2025-09 | G23: =COUNTIF('MRR Conglomerado'!E669:AT669,">0") -> 14 | H23: ='MRR Conglomerado'!AT669 -> 0
A24: ='MRR Conglomerado'!A750 -> VAPR870821D | B24: ='MRR Conglomerado'!B750 -> RODOLFO VALTIERRA PICOS | C24: ='MRR Conglomerado'!AH750 -> 5619.6094 | D24: =C24/$K$1 -> 297.57 | E24: =IF(D24<100,"Menos de 100 USD",IF(D24<500,"100 a 500 USD",IF(D24<2000,"500 a 2.000 USD","Más de 2.000 USD"))) -> 100 a 500 USD | F24: =LOOKUP(2,1/('MRR Conglomerado'!E750:AT750>0),'MRR Conglomerado'!$E$1:$AT$1) -> 2025-12 | G24: =COUNTIF('MRR Conglomerado'!E750:AT750,">0") -> 36 | H24: ='MRR Conglomerado'!AT750 -> 0
A25: ='MRR Conglomerado'!A517 -> OGA101029LS | B25: ='MRR Conglomerado'!B517 -> OPERADORA DE GRANOS Y ALMACENES | C25: ='MRR Conglomerado'!AH517 -> 5451.9106 | D25: =C25/$K$1 -> 288.69 | E25: =IF(D25<100,"Menos de 100 USD",IF(D25<500,"100 a 500 USD",IF(D25<2000,"500 a 2.000 USD","Más de 2.000 USD"))) -> 100 a 500 USD | F25: =LOOKUP(2,1/('MRR Conglomerado'!E517:AT517>0),'MRR Conglomerado'!$E$1:$AT$1) -> 2026-02 | G25: =COUNTIF('MRR Conglomerado'!E517:AT517,">0") -> 23 | H25: ='MRR Conglomerado'!AT517 -> 0
A26: ='MRR Conglomerado'!A634 -> SAC18120569 | B26: ='MRR Conglomerado'!B634 -> SERVICIOS DE AUTOTRANSPORTE CAZAMA | C26: ='MRR Conglomerado'!AH634 -> 5395.0668 | D26: =C26/$K$1 -> 285.68 | E26: =IF(D26<100,"Menos de 100 USD",IF(D26<500,"100 a 500 USD",IF(D26<2000,"500 a 2.000 USD","Más de 2.000 USD"))) -> 100 a 500 USD | F26: =LOOKUP(2,1/('MRR Conglomerado'!E634:AT634>0),'MRR Conglomerado'!$E$1:$AT$1) -> 2026-01 | G26: =COUNTIF('MRR Conglomerado'!E634:AT634,">0") -> 13 | H26: ='MRR Conglomerado'!AT634 -> 0
A27: ='MRR Conglomerado'!A382 -> HUC21101387 | B27: ='MRR Conglomerado'!B382 -> HAICO URBANIZACION Y CONSTRUCCION | C27: ='MRR Conglomerado'!AH382 -> 5361.6403 | D27: =C27/$K$1 -> 283.91 | E27: =IF(D27<100,"Menos de 100 USD",IF(D27<500,"100 a 500 USD",IF(D27<2000,"500 a 2.000 USD","Más de 2.000 USD"))) -> 100 a 500 USD | F27: =LOOKUP(2,1/('MRR Conglomerado'!E382:AT382>0),'MRR Conglomerado'!$E$1:$AT$1) -> 2025-11 | G27: =COUNTIF('MRR Conglomerado'!E382:AT382,">0") -> 28 | H27: ='MRR Conglomerado'!AT382 -> 0
A28: ='MRR Conglomerado'!A262 -> ETP2208223L | B28: ='MRR Conglomerado'!B262 -> ESQUEMAS TACTICOS DE PROMOCION | C28: ='MRR Conglomerado'!AH262 -> 4200.024 | D28: =C28/$K$1 -> 222.4 | E28: =IF(D28<100,"Menos de 100 USD",IF(D28<500,"100 a 500 USD",IF(D28<2000,"500 a 2.000 USD","Más de 2.000 USD"))) -> 100 a 500 USD | F28: =LOOKUP(2,1/('MRR Conglomerado'!E262:AT262>0),'MRR Conglomerado'!$E$1:$AT$1) -> 2025-07 | G28: =COUNTIF('MRR Conglomerado'!E262:AT262,">0") -> 6 | H28: ='MRR Conglomerado'!AT262 -> 0
A29: ='MRR Conglomerado'!A250 -> ENE150506UG | B29: ='MRR Conglomerado'!B250 -> ENESTAS | C29: ='MRR Conglomerado'!AH250 -> 4192.47 | D29: =C29/$K$1 -> 222 | E29: =IF(D29<100,"Menos de 100 USD",IF(D29<500,"100 a 500 USD",IF(D29<2000,"500 a 2.000 USD","Más de 2.000 USD"))) -> 100 a 500 USD | F29: =LOOKUP(2,1/('MRR Conglomerado'!E250:AT250>0),'MRR Conglomerado'!$E$1:$AT$1) -> 2026-01 | G29: =COUNTIF('MRR Conglomerado'!E250:AT250,">0") -> 13 | H29: ='MRR Conglomerado'!AT250 -> 0
A30: ='MRR Conglomerado'!A310 -> GCA100623EZ | B30: ='MRR Conglomerado'!B310 -> GRUPO CONSTRUCTOR AQUILES | C30: ='MRR Conglomerado'!AH310 -> 4149.9788 | D30: =C30/$K$1 -> 219.75 | E30: =IF(D30<100,"Menos de 100 USD",IF(D30<500,"100 a 500 USD",IF(D30<2000,"500 a 2.000 USD","Más de 2.000 USD"))) -> 100 a 500 USD | F30: =LOOKUP(2,1/('MRR Conglomerado'!E310:AT310>0),'MRR Conglomerado'!$E$1:$AT$1) -> 2025-10 | G30: =COUNTIF('MRR Conglomerado'!E310:AT310,">0") -> 5 | H30: ='MRR Conglomerado'!AT310 -> 0
A31: ='MRR Conglomerado'!A742 -> UCO040903MP | B31: ='MRR Conglomerado'!B742 -> UNIQUE COMM | C31: ='MRR Conglomerado'!AH742 -> 3875.9574 | D31: =C31/$K$1 -> 205.24 | E31: =IF(D31<100,"Menos de 100 USD",IF(D31<500,"100 a 500 USD",IF(D31<2000,"500 a 2.000 USD","Más de 2.000 USD"))) -> 100 a 500 USD | F31: =LOOKUP(2,1/('MRR Conglomerado'!E742:AT742>0),'MRR Conglomerado'!$E$1:$AT$1) -> 2026-01 | G31: =COUNTIF('MRR Conglomerado'!E742:AT742,">0") -> 14 | H31: ='MRR Conglomerado'!AT742 -> 0
A32: ='MRR Conglomerado'!A349 -> GNE21082028 | B32: ='MRR Conglomerado'!B349 -> GRUPO NEEF | C32: ='MRR Conglomerado'!AH349 -> 3560.0114 | D32: =C32/$K$1 -> 188.51 | E32: =IF(D32<100,"Menos de 100 USD",IF(D32<500,"100 a 500 USD",IF(D32<2000,"500 a 2.000 USD","Más de 2.000 USD"))) -> 100 a 500 USD | F32: =LOOKUP(2,1/('MRR Conglomerado'!E349:AT349>0),'MRR Conglomerado'!$E$1:$AT$1) -> 2025-07 | G32: =COUNTIF('MRR Conglomerado'!E349:AT349,">0") -> 6 | H32: ='MRR Conglomerado'!AT349 -> 0
A33: ='MRR Conglomerado'!A450 -> LSM020731CZ | B33: ='MRR Conglomerado'!B450 -> LEE SPRING DE MEXICO | C33: ='MRR Conglomerado'!AH450 -> 3554.9124 | D33: =C33/$K$1 -> 188.24 | E33: =IF(D33<100,"Menos de 100 USD",IF(D33<500,"100 a 500 USD",IF(D33<2000,"500 a 2.000 USD","Más de 2.000 USD"))) -> 100 a 500 USD | F33: =LOOKUP(2,1/('MRR Conglomerado'!E450:AT450>0),'MRR Conglomerado'!$E$1:$AT$1) -> 2025-06 | G33: =COUNTIF('MRR Conglomerado'!E450:AT450,">0") -> 5 | H33: ='MRR Conglomerado'!AT450 -> 0
A34: ='MRR Conglomerado'!A545 -> PBA191125B3 | B34: ='MRR Conglomerado'!B545 -> PALMERA BONITA ACAPULCO | C34: ='MRR Conglomerado'!AH545 -> 3516.7647 | D34: =C34/$K$1 -> 186.22 | E34: =IF(D34<100,"Menos de 100 USD",IF(D34<500,"100 a 500 USD",IF(D34<2000,"500 a 2.000 USD","Más de 2.000 USD"))) -> 100 a 500 USD | F34: =LOOKUP(2,1/('MRR Conglomerado'!E545:AT545>0),'MRR Conglomerado'!$E$1:$AT$1) -> 2025-09 | G34: =COUNTIF('MRR Conglomerado'!E545:AT545,">0") -> 17 | H34: ='MRR Conglomerado'!AT545 -> 0
A35: ='MRR Conglomerado'!A29 -> AEAR791019G | B35: ='MRR Conglomerado'!B29 -> RONALD ARELLANO ARELLANO | C35: ='MRR Conglomerado'!AH29 -> 3180.0451 | D35: =C35/$K$1 -> 168.39 | E35: =IF(D35<100,"Menos de 100 USD",IF(D35<500,"100 a 500 USD",IF(D35<2000,"500 a 2.000 USD","Más de 2.000 USD"))) -> 100 a 500 USD | F35: =LOOKUP(2,1/('MRR Conglomerado'!E29:AT29>0),'MRR Conglomerado'!$E$1:$AT$1) -> 2025-08 | G35: =COUNTIF('MRR Conglomerado'!E29:AT29,">0") -> 3 | H35: ='MRR Conglomerado'!AT29 -> 0
A36: ='MRR Conglomerado'!A264 -> EVN190625UL | B36: ='MRR Conglomerado'!B264 -> ENERGIA VERDE Y NEGOCIOS SUSTENTABLES | C36: ='MRR Conglomerado'!AH264 -> 2844.081 | D36: =C36/$K$1 -> 150.6 | E36: =IF(D36<100,"Menos de 100 USD",IF(D36<500,"100 a 500 USD",IF(D36<2000,"500 a 2.000 USD","Más de 2.000 USD"))) -> 100 a 500 USD | F36: =LOOKUP(2,1/('MRR Conglomerado'!E264:AT264>0),'MRR Conglomerado'!$E$1:$AT$1) -> 2026-05 | G36: =COUNTIF('MRR Conglomerado'!E264:AT264,">0") -> 19 | H36: ='MRR Conglomerado'!AT264 -> 0
A37: ='MRR Conglomerado'!A180 -> CTE1804309D | B37: ='MRR Conglomerado'!B180 -> CARIBE TAXI EXPRESS | C37: ='MRR Conglomerado'!AH180 -> 2699.9884 | D37: =C37/$K$1 -> 142.97 | E37: =IF(D37<100,"Menos de 100 USD",IF(D37<500,"100 a 500 USD",IF(D37<2000,"500 a 2.000 USD","Más de 2.000 USD"))) -> 100 a 500 USD | F37: =LOOKUP(2,1/('MRR Conglomerado'!E180:AT180>0),'MRR Conglomerado'!$E$1:$AT$1) -> 2026-01 | G37: =COUNTIF('MRR Conglomerado'!E180:AT180,">0") -> 8 | H37: ='MRR Conglomerado'!AT180 -> 0
A38: ='MRR Conglomerado'!A654 -> SEI240528FF | B38: ='MRR Conglomerado'!B654 -> SOLUCIONES EMPRESARIALES INTEGRALES LIZAMA | C38: ='MRR Conglomerado'!AH654 -> 2625.015 | D38: =C38/$K$1 -> 139 | E38: =IF(D38<100,"Menos de 100 USD",IF(D38<500,"100 a 500 USD",IF(D38<2000,"500 a 2.000 USD","Más de 2.000 USD"))) -> 100 a 500 USD | F38: =LOOKUP(2,1/('MRR Conglomerado'!E654:AT654>0),'MRR Conglomerado'!$E$1:$AT$1) -> 2025-06 | G38: =COUNTIF('MRR Conglomerado'!E654:AT654,">0") -> 3 | H38: ='MRR Conglomerado'!AT654 -> 0
A39: ='MRR Conglomerado'!A694 -> STI070725SA | B39: ='MRR Conglomerado'!B694 -> SOLUCIONES PARA TI | C39: ='MRR Conglomerado'!AH694 -> 2448.2514 | D39: =C39/$K$1 -> 129.64 | E39: =IF(D39<100,"Menos de 100 USD",IF(D39<500,"100 a 500 USD",IF(D39<2000,"500 a 2.000 USD","Más de 2.000 USD"))) -> 100 a 500 USD | F39: =LOOKUP(2,1/('MRR Conglomerado'!E694:AT694>0),'MRR Conglomerado'!$E$1:$AT$1) -> 2025-12 | G39: =COUNTIF('MRR Conglomerado'!E694:AT694,">0") -> 23 | H39: ='MRR Conglomerado'!AT694 -> 0
A40: ='MRR Conglomerado'!A679 -> SMM090918UU | B40: ='MRR Conglomerado'!B679 -> SERVICIOS MEDICOS MAGAMED | C40: ='MRR Conglomerado'!AH679 -> 2083.9597 | D40: =C40/$K$1 -> 110.35 | E40: =IF(D40<100,"Menos de 100 USD",IF(D40<500,"100 a 500 USD",IF(D40<2000,"500 a 2.000 USD","Más de 2.000 USD"))) -> 100 a 500 USD | F40: =LOOKUP(2,1/('MRR Conglomerado'!E679:AT679>0),'MRR Conglomerado'!$E$1:$AT$1) -> 2025-06 | G40: =COUNTIF('MRR Conglomerado'!E679:AT679,">0") -> 15 | H40: ='MRR Conglomerado'!AT679 -> 0
A41: ='MRR Conglomerado'!A19 -> ABY14100757 | B41: ='MRR Conglomerado'!B19 -> ABYGIM | C41: ='MRR Conglomerado'!AH19 -> 1890.0108 | D41: =C41/$K$1 -> 100.08 | E41: =IF(D41<100,"Menos de 100 USD",IF(D41<500,"100 a 500 USD",IF(D41<2000,"500 a 2.000 USD","Más de 2.000 USD"))) -> 100 a 500 USD | F41: =LOOKUP(2,1/('MRR Conglomerado'!E19:AT19>0),'MRR Conglomerado'!$E$1:$AT$1) -> 2026-01 | G41: =COUNTIF('MRR Conglomerado'!E19:AT19,">0") -> 21 | H41: ='MRR Conglomerado'!AT19 -> 0
A42: ='MRR Conglomerado'!A478 -> MIN180426CD | B42: ='MRR Conglomerado'!B478 -> MARVIC INGENIERIA | C42: ='MRR Conglomerado'!AH478 -> 1772.735 | D42: =C42/$K$1 -> 93.87 | E42: =IF(D42<100,"Menos de 100 USD",IF(D42<500,"100 a 500 USD",IF(D42<2000,"500 a 2.000 USD","Más de 2.000 USD"))) -> Menos de 100 USD | F42: =LOOKUP(2,1/('MRR Conglomerado'!E478:AT478>0),'MRR Conglomerado'!$E$1:$AT$1) -> 2025-07 | G42: =COUNTIF('MRR Conglomerado'!E478:AT478,">0") -> 23 | H42: ='MRR Conglomerado'!AT478 -> 0
A43: ='MRR Conglomerado'!A329 -> GEV1304128D | B43: ='MRR Conglomerado'!B329 -> GEVILLA | C43: ='MRR Conglomerado'!AH329 -> 1628.0758 | D43: =C43/$K$1 -> 86.21 | E43: =IF(D43<100,"Menos de 100 USD",IF(D43<500,"100 a 500 USD",IF(D43<2000,"500 a 2.000 USD","Más de 2.000 USD"))) -> Menos de 100 USD | F43: =LOOKUP(2,1/('MRR Conglomerado'!E329:AT329>0),'MRR Conglomerado'!$E$1:$AT$1) -> 2026-04 | G43: =COUNTIF('MRR Conglomerado'!E329:AT329,">0") -> 27 | H43: ='MRR Conglomerado'!AT329 -> 0
A44: ='MRR Conglomerado'!A284 -> FME160905EC | B44: ='MRR Conglomerado'!B284 -> FREEDOMPOP MEXICO | C44: ='MRR Conglomerado'!AH284 -> 1435.0711 | D44: =C44/$K$1 -> 75.99 | E44: =IF(D44<100,"Menos de 100 USD",IF(D44<500,"100 a 500 USD",IF(D44<2000,"500 a 2.000 USD","Más de 2.000 USD"))) -> Menos de 100 USD | F44: =LOOKUP(2,1/('MRR Conglomerado'!E284:AT284>0),'MRR Conglomerado'!$E$1:$AT$1) -> 2025-09 | G44: =COUNTIF('MRR Conglomerado'!E284:AT284,">0") -> 4 | H44: ='MRR Conglomerado'!AT284 -> 0
A45: ='MRR Conglomerado'!A242 -> ELP180201M2 | B45: ='MRR Conglomerado'!B242 -> ENTRETENIMIENTO LPBC | C45: ='MRR Conglomerado'!AH242 -> 1413.9199 | D45: =C45/$K$1 -> 74.87 | E45: =IF(D45<100,"Menos de 100 USD",IF(D45<500,"100 a 500 USD",IF(D45<2000,"500 a 2.000 USD","Más de 2.000 USD"))) -> Menos de 100 USD | F45: =LOOKUP(2,1/('MRR Conglomerado'!E242:AT242>0),'MRR Conglomerado'!$E$1:$AT$1) -> 2025-09 | G45: =COUNTIF('MRR Conglomerado'!E242:AT242,">0") -> 18 | H45: ='MRR Conglomerado'!AT242 -> 0
A46: ='MRR Conglomerado'!A610 -> REI160425MD | B46: ='MRR Conglomerado'!B610 -> REISIX | C46: ='MRR Conglomerado'!AH610 -> 1300.61 | D46: =C46/$K$1 -> 68.87 | E46: =IF(D46<100,"Menos de 100 USD",IF(D46<500,"100 a 500 USD",IF(D46<2000,"500 a 2.000 USD","Más de 2.000 USD"))) -> Menos de 100 USD | F46: =LOOKUP(2,1/('MRR Conglomerado'!E610:AT610>0),'MRR Conglomerado'!$E$1:$AT$1) -> 2025-09 | G46: =COUNTIF('MRR Conglomerado'!E610:AT610,">0") -> 13 | H46: ='MRR Conglomerado'!AT610 -> 0
A47: ='MRR Conglomerado'!A460 -> MAS220617T3 | B47: ='MRR Conglomerado'!B460 -> MEZCLILLEROS ASOCIADOS | C47: ='MRR Conglomerado'!AH460 -> 1278.3256 | D47: =C47/$K$1 -> 67.69 | E47: =IF(D47<100,"Menos de 100 USD",IF(D47<500,"100 a 500 USD",IF(D47<2000,"500 a 2.000 USD","Más de 2.000 USD"))) -> Menos de 100 USD | F47: =LOOKUP(2,1/('MRR Conglomerado'!E460:AT460>0),'MRR Conglomerado'!$E$1:$AT$1) -> 2025-11 | G47: =COUNTIF('MRR Conglomerado'!E460:AT460,">0") -> 35 | H47: ='MRR Conglomerado'!AT460 -> 0
A48: ='MRR Conglomerado'!A392 -> ICA230127AT | B48: ='MRR Conglomerado'!B392 -> IME CANCUN | C48: ='MRR Conglomerado'!AH392 -> 1260.0072 | D48: =C48/$K$1 -> 66.72 | E48: =IF(D48<100,"Menos de 100 USD",IF(D48<500,"100 a 500 USD",IF(D48<2000,"500 a 2.000 USD","Más de 2.000 USD"))) -> Menos de 100 USD | F48: =LOOKUP(2,1/('MRR Conglomerado'!E392:AT392>0),'MRR Conglomerado'!$E$1:$AT$1) -> 2025-06 | G48: =COUNTIF('MRR Conglomerado'!E392:AT392,">0") -> 7 | H48: ='MRR Conglomerado'!AT392 -> 0
A49: ='MRR Conglomerado'!A76 -> BGM191223LI | B49: ='MRR Conglomerado'!B76 -> BOTICAS GRIEGAS DE MEXICO | C49: ='MRR Conglomerado'!AH76 -> 1199.9529 | D49: =C49/$K$1 -> 63.54 | E49: =IF(D49<100,"Menos de 100 USD",IF(D49<500,"100 a 500 USD",IF(D49<2000,"500 a 2.000 USD","Más de 2.000 USD"))) -> Menos de 100 USD | F49: =LOOKUP(2,1/('MRR Conglomerado'!E76:AT76>0),'MRR Conglomerado'!$E$1:$AT$1) -> 2026-02 | G49: =COUNTIF('MRR Conglomerado'!E76:AT76,">0") -> 15 | H49: ='MRR Conglomerado'!AT76 -> 0
A50: ='MRR Conglomerado'!A102 -> CBA11111137 | B50: ='MRR Conglomerado'!B102 -> CONSTRUCTORA BALBEK | C50: ='MRR Conglomerado'!AH102 -> 1144.0533 | D50: =C50/$K$1 -> 60.58 | E50: =IF(D50<100,"Menos de 100 USD",IF(D50<500,"100 a 500 USD",IF(D50<2000,"500 a 2.000 USD","Más de 2.000 USD"))) -> Menos de 100 USD | F50: =LOOKUP(2,1/('MRR Conglomerado'!E102:AT102>0),'MRR Conglomerado'!$E$1:$AT$1) -> 2025-12 | G50: =COUNTIF('MRR Conglomerado'!E102:AT102,">0") -> 14 | H50: ='MRR Conglomerado'!AT102 -> 0
A51: ='MRR Conglomerado'!A65 -> AUT160620UK | B51: ='MRR Conglomerado'!B65 -> AUTSOL | C51: ='MRR Conglomerado'!AH65 -> 1140.0874 | D51: =C51/$K$1 -> 60.37 | E51: =IF(D51<100,"Menos de 100 USD",IF(D51<500,"100 a 500 USD",IF(D51<2000,"500 a 2.000 USD","Más de 2.000 USD"))) -> Menos de 100 USD | F51: =LOOKUP(2,1/('MRR Conglomerado'!E65:AT65>0),'MRR Conglomerado'!$E$1:$AT$1) -> 2025-12 | G51: =COUNTIF('MRR Conglomerado'!E65:AT65,">0") -> 11 | H51: ='MRR Conglomerado'!AT65 -> 0
A52: ='MRR Conglomerado'!A684 -> SOA051222UW | B52: ='MRR Conglomerado'!B684 -> SERVICIOS OPERATIVOS DEL ATLANTICO | C52: ='MRR Conglomerado'!AH684 -> 1117.992 | D52: =C52/$K$1 -> 59.2 | E52: =IF(D52<100,"Menos de 100 USD",IF(D52<500,"100 a 500 USD",IF(D52<2000,"500 a 2.000 USD","Más de 2.000 USD"))) -> Menos de 100 USD | F52: =LOOKUP(2,1/('MRR Conglomerado'!E684:AT684>0),'MRR Conglomerado'!$E$1:$AT$1) -> 2025-11 | G52: =COUNTIF('MRR Conglomerado'!E684:AT684,">0") -> 10 | H52: ='MRR Conglomerado'!AT684 -> 0
A53: ='MRR Conglomerado'!A216 -> DUD0806184D | B53: ='MRR Conglomerado'!B216 -> DESARROLLADORA URBANISTICA DE OCCIDENTE | C53: ='MRR Conglomerado'!AH216 -> 1094.1969 | D53: =C53/$K$1 -> 57.94 | E53: =IF(D53<100,"Menos de 100 USD",IF(D53<500,"100 a 500 USD",IF(D53<2000,"500 a 2.000 USD","Más de 2.000 USD"))) -> Menos de 100 USD | F53: =LOOKUP(2,1/('MRR Conglomerado'!E216:AT216>0),'MRR Conglomerado'!$E$1:$AT$1) -> 2025-11 | G53: =COUNTIF('MRR Conglomerado'!E216:AT216,">0") -> 29 | H53: ='MRR Conglomerado'!AT216 -> 0
A54: ='MRR Conglomerado'!A434 -> LBG211011SX | B54: ='MRR Conglomerado'!B434 -> LUXURY BUILDING GROUP | C54: ='MRR Conglomerado'!AH434 -> 1050.006 | D54: =C54/$K$1 -> 55.6 | E54: =IF(D54<100,"Menos de 100 USD",IF(D54<500,"100 a 500 USD",IF(D54<2000,"500 a 2.000 USD","Más de 2.000 USD"))) -> Menos de 100 USD | F54: =LOOKUP(2,1/('MRR Conglomerado'!E434:AT434>0),'MRR Conglomerado'!$E$1:$AT$1) -> 2025-09 | G54: =COUNTIF('MRR Conglomerado'!E434:AT434,">0") -> 4 | H54: ='MRR Conglomerado'!AT434 -> 0
A55: ='MRR Conglomerado'!A137 -> CHS190405V5 | B55: ='MRR Conglomerado'!B137 -> CONVERTIDOR DE HIGIENICO Y SERVILLETA | C55: ='MRR Conglomerado'!AH137 -> 936.50715 | D55: =C55/$K$1 -> 49.59 | E55: =IF(D55<100,"Menos de 100 USD",IF(D55<500,"100 a 500 USD",IF(D55<2000,"500 a 2.000 USD","Más de 2.000 USD"))) -> Menos de 100 USD | F55: =LOOKUP(2,1/('MRR Conglomerado'!E137:AT137>0),'MRR Conglomerado'!$E$1:$AT$1) -> 2025-06 | G55: =COUNTIF('MRR Conglomerado'!E137:AT137,">0") -> 30 | H55: ='MRR Conglomerado'!AT137 -> 0
A56: ='MRR Conglomerado'!A651 -> SDM24031392 | B56: ='MRR Conglomerado'!B651 -> SERVICIOS DCOMERCIALES MAXMEX | C56: ='MRR Conglomerado'!AH651 -> 913.46745 | D56: =C56/$K$1 -> 48.37 | E56: =IF(D56<100,"Menos de 100 USD",IF(D56<500,"100 a 500 USD",IF(D56<2000,"500 a 2.000 USD","Más de 2.000 USD"))) -> Menos de 100 USD | F56: =LOOKUP(2,1/('MRR Conglomerado'!E651:AT651>0),'MRR Conglomerado'!$E$1:$AT$1) -> 2025-07 | G56: =COUNTIF('MRR Conglomerado'!E651:AT651,">0") -> 12 | H56: ='MRR Conglomerado'!AT651 -> 0
A57: ='MRR Conglomerado'!A88 -> CAEE6306059 | B57: ='MRR Conglomerado'!B88 -> EDWIN MARTIN CAUICH ESCALANTE | C57: ='MRR Conglomerado'!AH88 -> 881.9295 | D57: =C57/$K$1 -> 46.7 | E57: =IF(D57<100,"Menos de 100 USD",IF(D57<500,"100 a 500 USD",IF(D57<2000,"500 a 2.000 USD","Más de 2.000 USD"))) -> Menos de 100 USD | F57: =LOOKUP(2,1/('MRR Conglomerado'!E88:AT88>0),'MRR Conglomerado'!$E$1:$AT$1) -> 2025-08 | G57: =COUNTIF('MRR Conglomerado'!E88:AT88,">0") -> 9 | H57: ='MRR Conglomerado'!AT88 -> 0
A58: ='MRR Conglomerado'!A298 -> FUCH820720Q | B58: ='MRR Conglomerado'!B298 -> HECTOR FUERTES CARDENAS | C58: ='MRR Conglomerado'!AH298 -> 878.1525 | D58: =C58/$K$1 -> 46.5 | E58: =IF(D58<100,"Menos de 100 USD",IF(D58<500,"100 a 500 USD",IF(D58<2000,"500 a 2.000 USD","Más de 2.000 USD"))) -> Menos de 100 USD | F58: =LOOKUP(2,1/('MRR Conglomerado'!E298:AT298>0),'MRR Conglomerado'!$E$1:$AT$1) -> 2025-11 | G58: =COUNTIF('MRR Conglomerado'!E298:AT298,">0") -> 35 | H58: ='MRR Conglomerado'!AT298 -> 0
A59: ='MRR Conglomerado'!A541 -> PAL250303Q4 | B59: ='MRR Conglomerado'!B541 -> PUNTO ALQUIMIA | C59: ='MRR Conglomerado'!AH541 -> 878.1525 | D59: =C59/$K$1 -> 46.5 | E59: =IF(D59<100,"Menos de 100 USD",IF(D59<500,"100 a 500 USD",IF(D59<2000,"500 a 2.000 USD","Más de 2.000 USD"))) -> Menos de 100 USD | F59: =LOOKUP(2,1/('MRR Conglomerado'!E541:AT541>0),'MRR Conglomerado'!$E$1:$AT$1) -> 2026-02 | G59: =COUNTIF('MRR Conglomerado'!E541:AT541,">0") -> 9 | H59: ='MRR Conglomerado'!AT541 -> 0
A60: ='MRR Conglomerado'!A145 -> CJA240311RB | B60: ='MRR Conglomerado'!B145 -> COMERCIALIZADORA JAGAKAR | C60: ='MRR Conglomerado'!AH145 -> 850.5804 | D60: =C60/$K$1 -> 45.04 | E60: =IF(D60<100,"Menos de 100 USD",IF(D60<500,"100 a 500 USD",IF(D60<2000,"500 a 2.000 USD","Más de 2.000 USD"))) -> Menos de 100 USD | F60: =LOOKUP(2,1/('MRR Conglomerado'!E145:AT145>0),'MRR Conglomerado'!$E$1:$AT$1) -> 2025-07 | G60: =COUNTIF('MRR Conglomerado'!E145:AT145,">0") -> 12 | H60: ='MRR Conglomerado'!AT145 -> 0
A61: ='MRR Conglomerado'!A288 -> FON120110S6 | B61: ='MRR Conglomerado'!B288 -> FEDERACION OBRERA NACIONALISTA | C61: ='MRR Conglomerado'!AH288 -> 819.04245 | D61: =C61/$K$1 -> 43.37 | E61: =IF(D61<100,"Menos de 100 USD",IF(D61<500,"100 a 500 USD",IF(D61<2000,"500 a 2.000 USD","Más de 2.000 USD"))) -> Menos de 100 USD | F61: =LOOKUP(2,1/('MRR Conglomerado'!E288:AT288>0),'MRR Conglomerado'!$E$1:$AT$1) -> 2026-01 | G61: =COUNTIF('MRR Conglomerado'!E288:AT288,">0") -> 14 | H61: ='MRR Conglomerado'!AT288 -> 0
A62: ='MRR Conglomerado'!A371 -> HESE6103164 | B62: ='MRR Conglomerado'!B371 -> MARIA EUGENIA HERNANDEZ SANCHEZ | C62: ='MRR Conglomerado'!AH371 -> 781.65015 | D62: =C62/$K$1 -> 41.39 | E62: =IF(D62<100,"Menos de 100 USD",IF(D62<500,"100 a 500 USD",IF(D62<2000,"500 a 2.000 USD","Más de 2.000 USD"))) -> Menos de 100 USD | F62: =LOOKUP(2,1/('MRR Conglomerado'!E371:AT371>0),'MRR Conglomerado'!$E$1:$AT$1) -> 2025-06 | G62: =COUNTIF('MRR Conglomerado'!E371:AT371,">0") -> 17 | H62: ='MRR Conglomerado'!AT371 -> 0
A63: ='MRR Conglomerado'!A380 -> HTR1511103A | B63: ='MRR Conglomerado'!B380 -> HARI TRADING | C63: ='MRR Conglomerado'!AH380 -> 769.94145 | D63: =C63/$K$1 -> 40.77 | E63: =IF(D63<100,"Menos de 100 USD",IF(D63<500,"100 a 500 USD",IF(D63<2000,"500 a 2.000 USD","Más de 2.000 USD"))) -> Menos de 100 USD | F63: =LOOKUP(2,1/('MRR Conglomerado'!E380:AT380>0),'MRR Conglomerado'!$E$1:$AT$1) -> 2025-06 | G63: =COUNTIF('MRR Conglomerado'!E380:AT380,">0") -> 8 | H63: ='MRR Conglomerado'!AT380 -> 0
A64: ='MRR Conglomerado'!A94 -> CAMH990519T | B64: ='MRR Conglomerado'!B94 -> HECTOR ANTONIO CAMARGO MORALES | C64: ='MRR Conglomerado'!AH94 -> 749.92335 | D64: =C64/$K$1 -> 39.71 | E64: =IF(D64<100,"Menos de 100 USD",IF(D64<500,"100 a 500 USD",IF(D64<2000,"500 a 2.000 USD","Más de 2.000 USD"))) -> Menos de 100 USD | F64: =LOOKUP(2,1/('MRR Conglomerado'!E94:AT94>0),'MRR Conglomerado'!$E$1:$AT$1) -> 2025-06 | G64: =COUNTIF('MRR Conglomerado'!E94:AT94,">0") -> 8 | H64: ='MRR Conglomerado'!AT94 -> 0
A65: ='MRR Conglomerado'!A421 -> JAV14112059 | B65: ='MRR Conglomerado'!B421 -> JUF ACTIVANDO VALORES | C65: ='MRR Conglomerado'!AH421 -> 749.92335 | D65: =C65/$K$1 -> 39.71 | E65: =IF(D65<100,"Menos de 100 USD",IF(D65<500,"100 a 500 USD",IF(D65<2000,"500 a 2.000 USD","Más de 2.000 USD"))) -> Menos de 100 USD | F65: =LOOKUP(2,1/('MRR Conglomerado'!E421:AT421>0),'MRR Conglomerado'!$E$1:$AT$1) -> 2025-12 | G65: =COUNTIF('MRR Conglomerado'!E421:AT421,">0") -> 14 | H65: ='MRR Conglomerado'!AT421 -> 0
A66: ='MRR Conglomerado'!A512 -> OAN13040289 | B66: ='MRR Conglomerado'!B512 -> ORTOPEDIA ANA | C66: ='MRR Conglomerado'!AH512 -> 749.92335 | D66: =C66/$K$1 -> 39.71 | E66: =IF(D66<100,"Menos de 100 USD",IF(D66<500,"100 a 500 USD",IF(D66<2000,"500 a 2.000 USD","Más de 2.000 USD"))) -> Menos de 100 USD | F66: =LOOKUP(2,1/('MRR Conglomerado'!E512:AT512>0),'MRR Conglomerado'!$E$1:$AT$1) -> 2025-11 | G66: =COUNTIF('MRR Conglomerado'!E512:AT512,">0") -> 15 | H66: ='MRR Conglomerado'!AT512 -> 0
A67: ='MRR Conglomerado'!A642 -> SBC070427N3 | B67: ='MRR Conglomerado'!B642 -> SOUTH BAJA CONSTRUCTORA | C67: ='MRR Conglomerado'!AH642 -> 704.0328 | D67: =C67/$K$1 -> 37.28 | E67: =IF(D67<100,"Menos de 100 USD",IF(D67<500,"100 a 500 USD",IF(D67<2000,"500 a 2.000 USD","Más de 2.000 USD"))) -> Menos de 100 USD | F67: =LOOKUP(2,1/('MRR Conglomerado'!E642:AT642>0),'MRR Conglomerado'!$E$1:$AT$1) -> 2026-04 | G67: =COUNTIF('MRR Conglomerado'!E642:AT642,">0") -> 26 | H67: ='MRR Conglomerado'!AT642 -> 0
A68: ='MRR Conglomerado'!A587 -> PRI0306054C | B68: ='MRR Conglomerado'!B587 -> PRO RIEGO | C68: ='MRR Conglomerado'!AH587 -> 681.93735 | D68: =C68/$K$1 -> 36.11 | E68: =IF(D68<100,"Menos de 100 USD",IF(D68<500,"100 a 500 USD",IF(D68<2000,"500 a 2.000 USD","Más de 2.000 USD"))) -> Menos de 100 USD | F68: =LOOKUP(2,1/('MRR Conglomerado'!E587:AT587>0),'MRR Conglomerado'!$E$1:$AT$1) -> 2026-04 | G68: =COUNTIF('MRR Conglomerado'!E587:AT587,">0") -> 17 | H68: ='MRR Conglomerado'!AT587 -> 0
A69: ='MRR Conglomerado'!A631 -> RURR800901H | B69: ='MRR Conglomerado'!B631 -> REMEDIOS SERGIO ALBERTO RUIZ RAMIREZ | C69: ='MRR Conglomerado'!AH631 -> 599.97645 | D69: =C69/$K$1 -> 31.77 | E69: =IF(D69<100,"Menos de 100 USD",IF(D69<500,"100 a 500 USD",IF(D69<2000,"500 a 2.000 USD","Más de 2.000 USD"))) -> Menos de 100 USD | F69: =LOOKUP(2,1/('MRR Conglomerado'!E631:AT631>0),'MRR Conglomerado'!$E$1:$AT$1) -> 2025-11 | G69: =COUNTIF('MRR Conglomerado'!E631:AT631,">0") -> 6 | H69: ='MRR Conglomerado'!AT631 -> 0
A70: ='MRR Conglomerado'!A8 -> AAGA570212I | B70: ='MRR Conglomerado'!B8 -> ARTURO ALMARAZ GARCIA | C70: ='MRR Conglomerado'!AH8 -> 562.773 | D70: =C70/$K$1 -> 29.8 | E70: =IF(D70<100,"Menos de 100 USD",IF(D70<500,"100 a 500 USD",IF(D70<2000,"500 a 2.000 USD","Más de 2.000 USD"))) -> Menos de 100 USD | F70: =LOOKUP(2,1/('MRR Conglomerado'!E8:AT8>0),'MRR Conglomerado'!$E$1:$AT$1) -> 2025-06 | G70: =COUNTIF('MRR Conglomerado'!E8:AT8,">0") -> 22 | H70: ='MRR Conglomerado'!AT8 -> 0
A71: ='MRR Conglomerado'!A38 -> AIN230522RC | B71: ='MRR Conglomerado'!B38 -> AGRAIRON INDUSTRIAL | C71: ='MRR Conglomerado'!AH38 -> 559.94025 | D71: =C71/$K$1 -> 29.65 | E71: =IF(D71<100,"Menos de 100 USD",IF(D71<500,"100 a 500 USD",IF(D71<2000,"500 a 2.000 USD","Más de 2.000 USD"))) -> Menos de 100 USD | F71: =LOOKUP(2,1/('MRR Conglomerado'!E38:AT38>0),'MRR Conglomerado'!$E$1:$AT$1) -> 2025-10 | G71: =COUNTIF('MRR Conglomerado'!E38:AT38,">0") -> 6 | H71: ='MRR Conglomerado'!AT38 -> 0
A72: ='MRR Conglomerado'!A625 -> ROOR9108136 | B72: ='MRR Conglomerado'!B625 -> REYMUNDO ROSAS OLVERA | C72: ='MRR Conglomerado'!AH625 -> 521.03715 | D72: =C72/$K$1 -> 27.59 | E72: =IF(D72<100,"Menos de 100 USD",IF(D72<500,"100 a 500 USD",IF(D72<2000,"500 a 2.000 USD","Más de 2.000 USD"))) -> Menos de 100 USD | F72: =LOOKUP(2,1/('MRR Conglomerado'!E625:AT625>0),'MRR Conglomerado'!$E$1:$AT$1) -> 2025-06 | G72: =COUNTIF('MRR Conglomerado'!E625:AT625,">0") -> 15 | H72: ='MRR Conglomerado'!AT625 -> 0
A73: ='MRR Conglomerado'!A693 -> SSP240411D6 | B73: ='MRR Conglomerado'!B693 -> SAHORIMA SERVICIOS PROFESIONALES | C73: ='MRR Conglomerado'!AH693 -> 504.04065 | D73: =C73/$K$1 -> 26.69 | E73: =IF(D73<100,"Menos de 100 USD",IF(D73<500,"100 a 500 USD",IF(D73<2000,"500 a 2.000 USD","Más de 2.000 USD"))) -> Menos de 100 USD | F73: =LOOKUP(2,1/('MRR Conglomerado'!E693:AT693>0),'MRR Conglomerado'!$E$1:$AT$1) -> 2025-07 | G73: =COUNTIF('MRR Conglomerado'!E693:AT693,">0") -> 12 | H73: ='MRR Conglomerado'!AT693 -> 0
A74: ='MRR Conglomerado'!A215 -> DSE221109CB | B74: ='MRR Conglomerado'!B215 -> DOORVEL SERVICES | C74: ='MRR Conglomerado'!AH215 -> 487.6107 | D74: =C74/$K$1 -> 25.82 | E74: =IF(D74<100,"Menos de 100 USD",IF(D74<500,"100 a 500 USD",IF(D74<2000,"500 a 2.000 USD","Más de 2.000 USD"))) -> Menos de 100 USD | F74: =LOOKUP(2,1/('MRR Conglomerado'!E215:AT215>0),'MRR Conglomerado'!$E$1:$AT$1) -> 2026-01 | G74: =COUNTIF('MRR Conglomerado'!E215:AT215,">0") -> 23 | H74: ='MRR Conglomerado'!AT215 -> 0
A75: ='MRR Conglomerado'!A650 -> SDI211118U4 | B75: ='MRR Conglomerado'!B650 -> SPORTS DATA INTELLIGENCE | C75: ='MRR Conglomerado'!AH650 -> 461.9271 | D75: =C75/$K$1 -> 24.46 | E75: =IF(D75<100,"Menos de 100 USD",IF(D75<500,"100 a 500 USD",IF(D75<2000,"500 a 2.000 USD","Más de 2.000 USD"))) -> Menos de 100 USD | F75: =LOOKUP(2,1/('MRR Conglomerado'!E650:AT650>0),'MRR Conglomerado'!$E$1:$AT$1) -> 2025-09 | G75: =COUNTIF('MRR Conglomerado'!E650:AT650,">0") -> 15 | H75: ='MRR Conglomerado'!AT650 -> 0
A76: ='MRR Conglomerado'!A369 -> HEB230509UV | B76: ='MRR Conglomerado'!B369 -> HOC EST BONUM | C76: ='MRR Conglomerado'!AH369 -> 437.56545 | D76: =C76/$K$1 -> 23.17 | E76: =IF(D76<100,"Menos de 100 USD",IF(D76<500,"100 a 500 USD",IF(D76<2000,"500 a 2.000 USD","Más de 2.000 USD"))) -> Menos de 100 USD | F76: =LOOKUP(2,1/('MRR Conglomerado'!E369:AT369>0),'MRR Conglomerado'!$E$1:$AT$1) -> 2026-04 | G76: =COUNTIF('MRR Conglomerado'!E369:AT369,">0") -> 12 | H76: ='MRR Conglomerado'!AT369 -> 0
A77: ='MRR Conglomerado'!A469 -> MER140402BP | B77: ='MRR Conglomerado'!B469 -> MERCAFLASH | C77: ='MRR Conglomerado'!AH469 -> 420.0024 | D77: =C77/$K$1 -> 22.24 | E77: =IF(D77<100,"Menos de 100 USD",IF(D77<500,"100 a 500 USD",IF(D77<2000,"500 a 2.000 USD","Más de 2.000 USD"))) -> Menos de 100 USD | F77: =LOOKUP(2,1/('MRR Conglomerado'!E469:AT469>0),'MRR Conglomerado'!$E$1:$AT$1) -> 2025-07 | G77: =COUNTIF('MRR Conglomerado'!E469:AT469,">0") -> 2 | H77: ='MRR Conglomerado'!AT469 -> 0
A78: ='MRR Conglomerado'!A93 -> CAGC780928U | B78: ='MRR Conglomerado'!B93 -> CECILIA CABRERA GARCIA | C78: ='MRR Conglomerado'!AH93 -> 375.0561 | D78: =C78/$K$1 -> 19.86 | E78: =IF(D78<100,"Menos de 100 USD",IF(D78<500,"100 a 500 USD",IF(D78<2000,"500 a 2.000 USD","Más de 2.000 USD"))) -> Menos de 100 USD | F78: =LOOKUP(2,1/('MRR Conglomerado'!E93:AT93>0),'MRR Conglomerado'!$E$1:$AT$1) -> 2025-06 | G78: =COUNTIF('MRR Conglomerado'!E93:AT93,">0") -> 17 | H78: ='MRR Conglomerado'!AT93 -> 0
A79: ='MRR Conglomerado'!A114 -> CCO220121FM | B79: ='MRR Conglomerado'!B114 -> CARBONO COMSOLTA | C79: ='MRR Conglomerado'!AH114 -> 350.1279 | D79: =C79/$K$1 -> 18.54 | E79: =IF(D79<100,"Menos de 100 USD",IF(D79<500,"100 a 500 USD",IF(D79<2000,"500 a 2.000 USD","Más de 2.000 USD"))) -> Menos de 100 USD | F79: =LOOKUP(2,1/('MRR Conglomerado'!E114:AT114>0),'MRR Conglomerado'!$E$1:$AT$1) -> 2026-02 | G79: =COUNTIF('MRR Conglomerado'!E114:AT114,">0") -> 34 | H79: ='MRR Conglomerado'!AT114 -> 0
A80: ='MRR Conglomerado'!A569 -> PLE190709UN | B80: ='MRR Conglomerado'!B569 -> PLEGMA | C80: ='MRR Conglomerado'!AH569 -> 338.60805 | D80: =C80/$K$1 -> 17.93 | E80: =IF(D80<100,"Menos de 100 USD",IF(D80<500,"100 a 500 USD",IF(D80<2000,"500 a 2.000 USD","Más de 2.000 USD"))) -> Menos de 100 USD | F80: =LOOKUP(2,1/('MRR Conglomerado'!E569:AT569>0),'MRR Conglomerado'!$E$1:$AT$1) -> 2025-12 | G80: =COUNTIF('MRR Conglomerado'!E569:AT569,">0") -> 25 | H80: ='MRR Conglomerado'!AT569 -> 0
A81: ='MRR Conglomerado'!A665 -> SID1312207I | B81: ='MRR Conglomerado'!B665 -> SERVICIOS INTEGRALES DIACONMA | C81: ='MRR Conglomerado'!AH665 -> 306.3147 | D81: =C81/$K$1 -> 16.22 | E81: =IF(D81<100,"Menos de 100 USD",IF(D81<500,"100 a 500 USD",IF(D81<2000,"500 a 2.000 USD","Más de 2.000 USD"))) -> Menos de 100 USD | F81: =LOOKUP(2,1/('MRR Conglomerado'!E665:AT665>0),'MRR Conglomerado'!$E$1:$AT$1) -> 2025-11 | G81: =COUNTIF('MRR Conglomerado'!E665:AT665,">0") -> 30 | H81: ='MRR Conglomerado'!AT665 -> 0
A82: ='MRR Conglomerado'!A479 -> MJO2007177J | B82: ='MRR Conglomerado'!B479 -> MERCADERIAS JON | C82: ='MRR Conglomerado'!AH479 -> 300.08265 | D82: =C82/$K$1 -> 15.89 | E82: =IF(D82<100,"Menos de 100 USD",IF(D82<500,"100 a 500 USD",IF(D82<2000,"500 a 2.000 USD","Más de 2.000 USD"))) -> Menos de 100 USD | F82: =LOOKUP(2,1/('MRR Conglomerado'!E479:AT479>0),'MRR Conglomerado'!$E$1:$AT$1) -> 2026-04 | G82: =COUNTIF('MRR Conglomerado'!E479:AT479,">0") -> 14 | H82: ='MRR Conglomerado'!AT479 -> 0
A83: ='MRR Conglomerado'!A330 -> GFA151022KI | B83: ='MRR Conglomerado'!B330 -> GO FARMACIAS | C83: ='MRR Conglomerado'!AH330 -> 260.613 | D83: =C83/$K$1 -> 13.8 | E83: =IF(D83<100,"Menos de 100 USD",IF(D83<500,"100 a 500 USD",IF(D83<2000,"500 a 2.000 USD","Más de 2.000 USD"))) -> Menos de 100 USD | F83: =LOOKUP(2,1/('MRR Conglomerado'!E330:AT330>0),'MRR Conglomerado'!$E$1:$AT$1) -> 2025-06 | G83: =COUNTIF('MRR Conglomerado'!E330:AT330,">0") -> 16 | H83: ='MRR Conglomerado'!AT330 -> 0
A84: ='MRR Conglomerado'!A455 -> MAC090304HT | B84: ='MRR Conglomerado'!B455 -> MANTENIMIENTO AUTOMOTRIZ DE CABO | C84: ='MRR Conglomerado'!AH455 -> 220.01025 | D84: =C84/$K$1 -> 11.65 | E84: =IF(D84<100,"Menos de 100 USD",IF(D84<500,"100 a 500 USD",IF(D84<2000,"500 a 2.000 USD","Más de 2.000 USD"))) -> Menos de 100 USD | F84: =LOOKUP(2,1/('MRR Conglomerado'!E455:AT455>0),'MRR Conglomerado'!$E$1:$AT$1) -> 2026-04 | G84: =COUNTIF('MRR Conglomerado'!E455:AT455,">0") -> 27 | H84: ='MRR Conglomerado'!AT455 -> 0
A85: ='MRR Conglomerado'!A766 -> VRE020626SQ | B85: ='MRR Conglomerado'!B766 -> VINICOLA REGIONAL DE ENSENADA | C85: ='MRR Conglomerado'!AH766 -> 158.44515 | D85: =C85/$K$1 -> 8.39 | E85: =IF(D85<100,"Menos de 100 USD",IF(D85<500,"100 a 500 USD",IF(D85<2000,"500 a 2.000 USD","Más de 2.000 USD"))) -> Menos de 100 USD | F85: =LOOKUP(2,1/('MRR Conglomerado'!E766:AT766>0),'MRR Conglomerado'!$E$1:$AT$1) -> 2025-06 | G85: =COUNTIF('MRR Conglomerado'!E766:AT766,">0") -> 5 | H85: ='MRR Conglomerado'!AT766 -> 0
A86: ='MRR Conglomerado'!A768 -> VVG040114UT | B86: ='MRR Conglomerado'!B768 -> VIÑAS DEL VALLE DE GUADALUPE | C86: ='MRR Conglomerado'!AH768 -> 118.78665 | D86: =C86/$K$1 -> 6.29 | E86: =IF(D86<100,"Menos de 100 USD",IF(D86<500,"100 a 500 USD",IF(D86<2000,"500 a 2.000 USD","Más de 2.000 USD"))) -> Menos de 100 USD | F86: =LOOKUP(2,1/('MRR Conglomerado'!E768:AT768>0),'MRR Conglomerado'!$E$1:$AT$1) -> 2026-01 | G86: =COUNTIF('MRR Conglomerado'!E768:AT768,">0") -> 11 | H86: ='MRR Conglomerado'!AT768 -> 0
A87: ='MRR Conglomerado'!A156 -> CMN210903IE | B87: ='MRR Conglomerado'!B156 -> COMERCIALIZADORA DE MATERIALES NEFS | C87: ='MRR Conglomerado'!AH156 -> 63.0759 | D87: =C87/$K$1 -> 3.34 | E87: =IF(D87<100,"Menos de 100 USD",IF(D87<500,"100 a 500 USD",IF(D87<2000,"500 a 2.000 USD","Más de 2.000 USD"))) -> Menos de 100 USD | F87: =LOOKUP(2,1/('MRR Conglomerado'!E156:AT156>0),'MRR Conglomerado'!$E$1:$AT$1) -> 2025-07 | G87: =COUNTIF('MRR Conglomerado'!E156:AT156,">0") -> 12 | H87: ='MRR Conglomerado'!AT156 -> 0
A88: TOTAL FUGA | B88: =COUNTA(A2:A87)&" conglomerados" -> 86 conglomerados | C88: =SUM(C2:C87) -> 323984.64 | D88: =SUM(D2:D87) -> 17155.66
A90: Fuga = conglomerados de la cohorte de jun-2026 (MRR > 0 en jun-2025) con MRR = 0 en jun-2026. Ordenados por MRR perdido. Filas referenciadas por fórmula a "MRR Conglomerado".

Sheet Notas
A1: NOTAS — MÉXICO, NRR DE JUNIO 2026, BASE MENSUAL, POR SEGMENTO DE TAMAÑO
A3: Definición: NRR del mes X = MRR de la cohorte en X / MRR en X-12, con cohorte = conglomerados de México con
A4: MRR > 0 en X-12 (se omiten los creados desde el mes siguiente). Todo el cálculo en MXN (moneda local = tipo de
A5: cambio original). USD sólo para segmentar por tamaño: MRR del mes base ÷ TC MXN/USD del mes base (hoja TC del
A6: archivo original): jun-25: 18,885 (ver celda B del detalle).
A7: Segmentos: < 100; 100 a 499,99; 500 a 1.999,99; 2.000 o más USD.
A9: Hoja "MRR Conglomerado": MRR mensual MXN por conglomerado (suma de sus RUT en México), extraído de
A10: "MRR Consolidado Moneda Loca v2" con trazabilidad en la columna C. Únicos valores pegados; el resto son fórmulas.
A11: Hoja "Detalle 2026-06": base (jun-25), actual (jun-26), NRR, tamaño USD, segmento y MRR retenido por conglomerado.
A12: Hoja "Resumen": N, fuga, % fuga, GRR y NRR por segmento y total, con fórmulas SUMIFS/COUNTIFS sobre los detalles.
A14: Advertencia: el segmento "Más de 2.000 USD" en México tiene ~5 cuentas; su NRR es muy sensible a una sola cuenta.
A16: Hoja "Detalle Fuga 2026-06": las 86 cuentas de la cohorte que quedaron en MRR = 0 en jun-2026, con su MRR perdido,
A17: tamaño, segmento, último mes con MRR y meses de vida. La fuga suma 323.985 MXN (~17.156 USD) = 15,6% del MRR base de la cohorte.
